setup.py
dsnd_probability_mc190200135/Binomialdistribution.py
dsnd_probability_mc190200135/Gaussiandistribution.py
dsnd_probability_mc190200135/Generaldistribution.py
dsnd_probability_mc190200135/__init__.py
dsnd_probability_mc190200135.egg-info/PKG-INFO
dsnd_probability_mc190200135.egg-info/SOURCES.txt
dsnd_probability_mc190200135.egg-info/dependency_links.txt
dsnd_probability_mc190200135.egg-info/not-zip-safe
dsnd_probability_mc190200135.egg-info/top_level.txt