Metadata-Version: 1.0
Name: dsnd-probability-mc190200135
Version: 0.1
Summary: Gaussian distributions and binomial distributions
Home-page: UNKNOWN
Author: test
Author-email: test@test.com
License: UNKNOWN
Platform: UNKNOWN
